<?xml version="1.0" encoding="UTF-8"?>
<configuration>
    <include resource="org/springframework/boot/logging/logback/defaults.xml"/>
    <include resource="org/springframework/boot/logging/logback/console-appender.xml"/>

    <springProperty scope="context" name="LOG_PATH" source="logging.file.path" defaultValue="logs"/>
    <springProperty scope="context" name="LOG_FILE" source="logging.file.name" defaultValue="${LOG_PATH}/photo-sync"/>

    <springProfile name="dev">
        <appender name="CONSOLE" class="ch.qos.logback.core.ConsoleAppender">
            <encoder>
                <pattern>%d{yyyy-MM-dd HH:mm:ss} [%highlight(%-5level)] %cyan(%logger{36}) - %msg%n</pattern>
            </encoder>
        </appender>
    </springProfile>

    <springProfile name="prod">
        <appender name="FILE" class="ch.qos.logback.core.rolling.RollingFileAppender">
            <file>${LOG_FILE}.log</file>
            <rollingPolicy class="ch.qos.logback.core.rolling.SizeAndTimeBasedRollingPolicy">
                <fileNamePattern>${LOG_FILE}.%d{yyyy-MM-dd}.%i.log</fileNamePattern>
                <maxFileSize>10MB</maxFileSize>
                <maxHistory>30</maxHistory>
                <totalSizeCap>1GB</totalSizeCap>
            </rollingPolicy>
            <encoder>
                <pattern>%d{yyyy-MM-dd HH:mm:ss} [%level] %logger{36} - %msg%n</pattern>
            </encoder>
        </appender>

        <appender name="ERROR_FILE" class="ch.qos.logback.core.rolling.RollingFileAppender">
            <file>${LOG_FILE}-error.log</file>
            <filter class="ch.qos.logback.classic.filter.ThresholdFilter">
                <level>ERROR</level>
            </filter>
            <rollingPolicy class="ch.qos.logback.core.rolling.SizeAndTimeBasedRollingPolicy">
                <fileNamePattern>${LOG_FILE}-error.%d{yyyy-MM-dd}.%i.log</fileNamePattern>
                <maxFileSize>10MB</maxFileSize>
                <maxHistory>30</maxHistory>
                <totalSizeCap>500MB</totalSizeCap>
            </rollingPolicy>
            <encoder>
                <pattern>%d{yyyy-MM-dd HH:mm:ss} [%level] %logger{36} - %msg%n</pattern>
            </encoder>
        </appender>
    </springProfile>

    <root level="${LOG_LEVEL:-INFO}">
        <appender-ref ref="CONSOLE"/>
        <appender-ref ref="FILE"/>
        <appender-ref ref="ERROR_FILE"/>
    </root>

    <logger name="com.github.bfalmeida.photosync" level="${APP_LOG_LEVEL:-DEBUG}"/>
</configuration>
